texlib/__init__.py
texlib/tex_utils.py
texlib2-1.0.0.dist-info/METADATA
texlib2-1.0.0.dist-info/WHEEL
texlib2-1.0.0.dist-info/top_level.txt
texlib2-1.0.0.dist-info/RECORD
