Metadata-Version: 2.1
Name: texlib2
Version: 1.0.0
Summary: A concise description of texlib
Home-page: http://example.com
Author: Georgii Ustinov
Author-email: ustinovgo@example.com
